SarthakFraction/Fraction.py
SarthakFraction/__init__.py
sarthakfraction-0.1.1.dist-info/licenses/LICENSE
sarthakfraction-0.1.1.dist-info/METADATA
sarthakfraction-0.1.1.dist-info/WHEEL
sarthakfraction-0.1.1.dist-info/top_level.txt
sarthakfraction-0.1.1.dist-info/RECORD
