Metadata-Version: 2.4
Name: SarthakFraction
Version: 0.1.1
Summary: A human-friendly Python package for fraction operations
Author-email: Sarthak Bora <youremail@example.com>
License: Copyright (c) 2018 The Python Packaging Authority
Project-URL: Homepage, https://github.com/Dev-SarthakBora/SarthakFraction
Requires-Python: >=3.7
License-File: LICENSE
Dynamic: license-file
